tek_awg.py
tek_awg-0.2.1.dist-info/LICENSE
tek_awg-0.2.1.dist-info/METADATA
tek_awg-0.2.1.dist-info/WHEEL
tek_awg-0.2.1.dist-info/top_level.txt
tek_awg-0.2.1.dist-info/RECORD
