Metadata-Version: 2.1
Name: tek-awg
Version: 0.2.1
Summary: Tektronix AWG interface for python
Home-page: https://github.com/qutech/TekAwg/
Author: Simon Humpohl
Author-email: simon.humpohl@rwth-aachen.de
License: GNU GPLv3
Platform: UNKNOWN
Requires-Dist: numpy
Requires-Dist: pyvisa
